src/control_unit.v
`timescale 1ns / 1ps

module control_unit (
    input wire [6:0] opcode,
    input wire [2:0] funct3,
    input wire [6:0] funct7,

    output reg [2:0] instruction_type,
    output reg [2:0] alu_control,

    output reg reg_write,
    output reg mem_read,
    output reg mem_write,
    output reg alu_src,
    output reg branch,
    output reg illegal_instruction
);

    localparam TYPE_UNKNOWN = 3'b000;
    localparam TYPE_R       = 3'b001;
    localparam TYPE_I       = 3'b010;
    localparam TYPE_LOAD    = 3'b011;
    localparam TYPE_STORE   = 3'b100;
    localparam TYPE_BRANCH  = 3'b101;

    localparam ALU_ADD = 3'b000;
    localparam ALU_SUB = 3'b001;

    always @(*) begin
        instruction_type    = TYPE_UNKNOWN;
        alu_control         = ALU_ADD;

        reg_write           = 1'b0;
        mem_read            = 1'b0;
        mem_write           = 1'b0;
        alu_src             = 1'b0;
        branch              = 1'b0;
        illegal_instruction = 1'b0;

        case (opcode)

            // ADD ve SUB
            7'b0110011: begin
                instruction_type = TYPE_R;
                reg_write        = 1'b1;

                if (
                    funct3 == 3'b000 &&
                    funct7 == 7'b0000000
                ) begin
                    alu_control = ALU_ADD;
                end
                else if (
                    funct3 == 3'b000 &&
                    funct7 == 7'b0100000
                ) begin
                    alu_control = ALU_SUB;
                end
                else begin
                    reg_write           = 1'b0;
                    illegal_instruction = 1'b1;
                end
            end

            // ADDI
            7'b0010011: begin
                instruction_type = TYPE_I;
                reg_write        = 1'b1;
                alu_src          = 1'b1;
                alu_control      = ALU_ADD;

                if (funct3 != 3'b000) begin
                    reg_write           = 1'b0;
                    illegal_instruction = 1'b1;
                end
            end

            // LW
            7'b0000011: begin
                instruction_type = TYPE_LOAD;
                reg_write        = 1'b1;
                mem_read         = 1'b1;
                alu_src          = 1'b1;
                alu_control      = ALU_ADD;

                if (funct3 != 3'b010) begin
                    reg_write           = 1'b0;
                    mem_read            = 1'b0;
                    illegal_instruction = 1'b1;
                end
            end

            // SW
            7'b0100011: begin
                instruction_type = TYPE_STORE;
                mem_write        = 1'b1;
                alu_src          = 1'b1;
                alu_control      = ALU_ADD;

                if (funct3 != 3'b010) begin
                    mem_write           = 1'b0;
                    illegal_instruction = 1'b1;
                end
            end

            // BEQ
            7'b1100011: begin
                instruction_type = TYPE_BRANCH;
                branch           = 1'b1;
                alu_control      = ALU_SUB;

                if (funct3 != 3'b000) begin
                    branch              = 1'b0;
                    illegal_instruction = 1'b1;
                end
            end

            default: begin
                illegal_instruction = 1'b1;
            end

        endcase
    end

endmodule

src/immediate_generator.v
`timescale 1ns / 1ps

module immediate_generator (
    input  wire [31:0] instruction,
    input  wire [6:0]  opcode,

    output reg signed [31:0] immediate
);

    always @(*) begin
        immediate = 32'sd0;

        case (opcode)

            // ADDI ve LW: I-Type
            7'b0010011,
            7'b0000011: begin
                immediate = {
                    {20{instruction[31]}},
                    instruction[31:20]
                };
            end

            // SW: S-Type
            7'b0100011: begin
                immediate = {
                    {20{instruction[31]}},
                    instruction[31:25],
                    instruction[11:7]
                };
            end

            // BEQ: B-Type
            7'b1100011: begin
                immediate = {
                    {19{instruction[31]}},
                    instruction[31],
                    instruction[7],
                    instruction[30:25],
                    instruction[11:8],
                    1'b0
                };
            end

            default: begin
                immediate = 32'sd0;
            end

        endcase
    end

endmodule

src/field_extractor.v
`timescale 1ns / 1ps

module field_extractor (
    input  wire [31:0] instruction,

    output wire [6:0] opcode,
    output wire [4:0] rd,
    output wire [2:0] funct3,
    output wire [4:0] rs1,
    output wire [4:0] rs2,
    output wire [6:0] funct7
);

    assign opcode = instruction[6:0];
    assign rd     = instruction[11:7];
    assign funct3 = instruction[14:12];
    assign rs1    = instruction[19:15];
    assign rs2    = instruction[24:20];
    assign funct7 = instruction[31:25];

endmodule

src/instruction_decoder.v
`timescale 1ns / 1ps

module instruction_decoder (
    input wire [31:0] instruction,

    output wire [6:0] opcode,
    output wire [4:0] rd,
    output wire [2:0] funct3,
    output wire [4:0] rs1,
    output wire [4:0] rs2,
    output wire [6:0] funct7,

    output wire [2:0] instruction_type,
    output wire [2:0] alu_control,
    output wire signed [31:0] immediate,

    output wire reg_write,
    output wire mem_read,
    output wire mem_write,
    output wire alu_src,
    output wire branch,
    output wire illegal_instruction
);

    field_extractor field_extractor_inst (
        .instruction(instruction),
        .opcode(opcode),
        .rd(rd),
        .funct3(funct3),
        .rs1(rs1),
        .rs2(rs2),
        .funct7(funct7)
    );

    immediate_generator immediate_generator_inst (
        .instruction(instruction),
        .opcode(opcode),
        .immediate(immediate)
    );

    control_unit control_unit_inst (
        .opcode(opcode),
        .funct3(funct3),
        .funct7(funct7),

        .instruction_type(instruction_type),
        .alu_control(alu_control),

        .reg_write(reg_write),
        .mem_read(mem_read),
        .mem_write(mem_write),
        .alu_src(alu_src),
        .branch(branch),
        .illegal_instruction(illegal_instruction)
    );

endmodule

tb/instruction_decoder_tb.v
`timescale 1ns / 1ps

module instruction_decoder_tb;

    reg [31:0] instruction;

    wire [6:0] opcode;
    wire [4:0] rd;
    wire [2:0] funct3;
    wire [4:0] rs1;
    wire [4:0] rs2;
    wire [6:0] funct7;

    wire [2:0] instruction_type;
    wire [2:0] alu_control;
    wire signed [31:0] immediate;

    wire reg_write;
    wire mem_read;
    wire mem_write;
    wire alu_src;
    wire branch;
    wire illegal_instruction;

    integer passed_tests;
    integer failed_tests;

    instruction_decoder dut (
        .instruction(instruction),

        .opcode(opcode),
        .rd(rd),
        .funct3(funct3),
        .rs1(rs1),
        .rs2(rs2),
        .funct7(funct7),

        .instruction_type(instruction_type),
        .alu_control(alu_control),
        .immediate(immediate),

        .reg_write(reg_write),
        .mem_read(mem_read),
        .mem_write(mem_write),
        .alu_src(alu_src),
        .branch(branch),
        .illegal_instruction(illegal_instruction)
    );

    /*
     * Beklenen değerlerle gerçek çıktıları karşılaştırır.
     */
    task check_test;

        input [8*30-1:0] test_name;

        input [2:0] expected_instruction_type;
        input [2:0] expected_alu_control;
        input signed [31:0] expected_immediate;

        input expected_reg_write;
        input expected_mem_read;
        input expected_mem_write;
        input expected_alu_src;
        input expected_branch;
        input expected_illegal;

        begin
            if (
                instruction_type    === expected_instruction_type &&
                alu_control         === expected_alu_control &&
                immediate           === expected_immediate &&
                reg_write           === expected_reg_write &&
                mem_read            === expected_mem_read &&
                mem_write           === expected_mem_write &&
                alu_src             === expected_alu_src &&
                branch              === expected_branch &&
                illegal_instruction === expected_illegal
            ) begin

                $display("[PASS] %s", test_name);
                passed_tests = passed_tests + 1;

            end
            else begin

                $display("[FAIL] %s", test_name);

                $display(
                    "  instruction_type: expected=%b actual=%b",
                    expected_instruction_type,
                    instruction_type
                );

                $display(
                    "  alu_control     : expected=%b actual=%b",
                    expected_alu_control,
                    alu_control
                );

                $display(
                    "  immediate       : expected=%0d actual=%0d",
                    expected_immediate,
                    immediate
                );

                $display(
                    "  reg_write       : expected=%b actual=%b",
                    expected_reg_write,
                    reg_write
                );

                $display(
                    "  mem_read        : expected=%b actual=%b",
                    expected_mem_read,
                    mem_read
                );

                $display(
                    "  mem_write       : expected=%b actual=%b",
                    expected_mem_write,
                    mem_write
                );

                $display(
                    "  alu_src         : expected=%b actual=%b",
                    expected_alu_src,
                    alu_src
                );

                $display(
                    "  branch          : expected=%b actual=%b",
                    expected_branch,
                    branch
                );

                $display(
                    "  illegal         : expected=%b actual=%b",
                    expected_illegal,
                    illegal_instruction
                );

                failed_tests = failed_tests + 1;
            end
        end
    endtask

    initial begin

        $dumpfile("wave/decoder.vcd");
        $dumpvars(0, instruction_decoder_tb);

        passed_tests = 0;
        failed_tests = 0;

        /*
         * TEST 1
         * ADD x5, x6, x7
         */
        instruction =
            32'b0000000_00111_00110_000_00101_0110011;

        #10;

        check_test(
            "ADD x5, x6, x7",
            3'b001,
            3'b000,
            32'sd0,
            1'b1,
            1'b0,
            1'b0,
            1'b0,
            1'b0,
            1'b0
        );

        /*
         * TEST 2
         * SUB x8, x5, x6
         */
        instruction =
            32'b0100000_00110_00101_000_01000_0110011;

        #10;

        check_test(
            "SUB x8, x5, x6",
            3'b001,
            3'b001,
            32'sd0,
            1'b1,
            1'b0,
            1'b0,
            1'b0,
            1'b0,
            1'b0
        );

        /*
         * TEST 3
         * ADDI x5, x6, 10
         */
        instruction =
            32'b000000001010_00110_000_00101_0010011;

        #10;

        check_test(
            "ADDI x5, x6, 10",
            3'b010,
            3'b000,
            32'sd10,
            1'b1,
            1'b0,
            1'b0,
            1'b1,
            1'b0,
            1'b0
        );

        /*
         * TEST 4
         * ADDI x5, x6, -4
         */
        instruction =
            32'b111111111100_00110_000_00101_0010011;

        #10;

        check_test(
            "ADDI x5, x6, -4",
            3'b010,
            3'b000,
            -32'sd4,
            1'b1,
            1'b0,
            1'b0,
            1'b1,
            1'b0,
            1'b0
        );

        /*
         * TEST 5
         * LW x5, 4(x6)
         */
        instruction =
            32'b000000000100_00110_010_00101_0000011;

        #10;

        check_test(
            "LW x5, 4(x6)",
            3'b011,
            3'b000,
            32'sd4,
            1'b1,
            1'b1,
            1'b0,
            1'b1,
            1'b0,
            1'b0
        );

        /*
         * TEST 6
         * SW x5, 4(x6)
         */
        instruction =
            32'b0000000_00101_00110_010_00100_0100011;

        #10;

        check_test(
            "SW x5, 4(x6)",
            3'b100,
            3'b000,
            32'sd4,
            1'b0,
            1'b0,
            1'b1,
            1'b1,
            1'b0,
            1'b0
        );

        /*
         * TEST 7
         * BEQ x5, x6, 8
         */
        instruction =
            32'b0000000_00110_00101_000_01000_1100011;

        #10;

        check_test(
            "BEQ x5, x6, 8",
            3'b101,
            3'b001,
            32'sd8,
            1'b0,
            1'b0,
            1'b0,
            1'b0,
            1'b1,
            1'b0
        );

        /*
         * TEST 8
         * Geçersiz opcode
         */
        instruction = 32'hFFFFFFFF;

        #10;

        check_test(
            "ILLEGAL INSTRUCTION",
            3'b000,
            3'b000,
            32'sd0,
            1'b0,
            1'b0,
            1'b0,
            1'b0,
            1'b0,
            1'b1
        );

        $display("");
        $display("========================================");
        $display("TEST SUMMARY");
        $display("========================================");
        $display("Passed tests : %0d", passed_tests);
        $display("Failed tests : %0d", failed_tests);
        $display("Total tests  : %0d", passed_tests + failed_tests);

        if (failed_tests == 0)
            $display("RESULT       : ALL TESTS PASSED");
        else
            $display("RESULT       : SOME TESTS FAILED");

        $display("========================================");

        #10;
        $finish;
    end

endmodule

decoder.vcd
$date
	Wed Aug  5 18:03:23 2026
$end
$version
	Icarus Verilog
$end
$timescale
	1ps
$end
$scope module instruction_decoder_tb $end
$var wire 5 ! rs2 [4:0] $end
$var wire 5 " rs1 [4:0] $end
$var wire 1 # reg_write $end
$var wire 5 $ rd [4:0] $end
$var wire 7 % opcode [6:0] $end
$var wire 1 & mem_write $end
$var wire 1 ' mem_read $end
$var wire 3 ( instruction_type [2:0] $end
$var wire 32 ) immediate [31:0] $end
$var wire 1 * illegal_instruction $end
$var wire 7 + funct7 [6:0] $end
$var wire 3 , funct3 [2:0] $end
$var wire 1 - branch $end
$var wire 1 . alu_src $end
$var wire 3 / alu_control [2:0] $end
$var reg 32 0 instruction [31:0] $end
$var integer 32 1 failed_tests [31:0] $end
$var integer 32 2 passed_tests [31:0] $end
$scope module dut $end
$var wire 32 3 instruction [31:0] $end
$var wire 5 4 rs2 [4:0] $end
$var wire 5 5 rs1 [4:0] $end
$var wire 1 # reg_write $end
$var wire 5 6 rd [4:0] $end
$var wire 7 7 opcode [6:0] $end
$var wire 1 & mem_write $end
$var wire 1 ' mem_read $end
$var wire 3 8 instruction_type [2:0] $end
$var wire 32 9 immediate [31:0] $end
$var wire 1 * illegal_instruction $end
$var wire 7 : funct7 [6:0] $end
$var wire 3 ; funct3 [2:0] $end
$var wire 1 - branch $end
$var wire 1 . alu_src $end
$var wire 3 < alu_control [2:0] $end
$scope module control_unit_inst $end
$var wire 7 = opcode [6:0] $end
$var wire 7 > funct7 [6:0] $end
$var wire 3 ? funct3 [2:0] $end
$var parameter 3 @ ALU_ADD $end
$var parameter 3 A ALU_SUB $end
$var parameter 3 B TYPE_BRANCH $end
$var parameter 3 C TYPE_I $end
$var parameter 3 D TYPE_LOAD $end
$var parameter 3 E TYPE_R $end
$var parameter 3 F TYPE_STORE $end
$var parameter 3 G TYPE_UNKNOWN $end
$var reg 3 H alu_control [2:0] $end
$var reg 1 . alu_src $end
$var reg 1 - branch $end
$var reg 1 * illegal_instruction $end
$var reg 3 I instruction_type [2:0] $end
$var reg 1 ' mem_read $end
$var reg 1 & mem_write $end
$var reg 1 # reg_write $end
$upscope $end
$scope module field_extractor_inst $end
$var wire 32 J instruction [31:0] $end
$var wire 5 K rs2 [4:0] $end
$var wire 5 L rs1 [4:0] $end
$var wire 5 M rd [4:0] $end
$var wire 7 N opcode [6:0] $end
$var wire 7 O funct7 [6:0] $end
$var wire 3 P funct3 [2:0] $end
$upscope $end
$scope module immediate_generator_inst $end
$var wire 32 Q instruction [31:0] $end
$var wire 7 R opcode [6:0] $end
$var reg 32 S immediate [31:0] $end
$upscope $end
$upscope $end
$scope task check_test $end
$var reg 3 T expected_alu_control [2:0] $end
$var reg 1 U expected_alu_src $end
$var reg 1 V expected_branch $end
$var reg 1 W expected_illegal $end
$var reg 32 X expected_immediate [31:0] $end
$var reg 3 Y expected_instruction_type [2:0] $end
$var reg 1 Z expected_mem_read $end
$var reg 1 [ expected_mem_write $end
$var reg 1 \ expected_reg_write $end
$var reg 240 ] test_name [239:0] $end
$upscope $end
$upscope $end
$enddefinitions $end
$comment Show the parameter values. $end
$dumpall
b0 G
b100 F
b1 E
b11 D
b10 C
b101 B
b1 A
b0 @
$end
#0
$dumpvars
bx ]
x\
x[
xZ
bx Y
bx X
xW
xV
xU
bx T
b0 S
b110011 R
b11100110000001010110011 Q
b0 P
b0 O
b110011 N
b101 M
b110 L
b111 K
b11100110000001010110011 J
b1 I
b0 H
b0 ?
b0 >
b110011 =
b0 <
b0 ;
b0 :
b0 9
b1 8
b110011 7
b101 6
b110 5
b111 4
b11100110000001010110011 3
b0 2
b0 1
b11100110000001010110011 0
b0 /
0.
0-
b0 ,
b0 +
0*
b0 )
b1 (
0'
0&
b110011 %
b101 $
1#
b110 "
b111 !
$end
#10000
b1 /
b1 <
b1 H
1#
b1 (
b1 8
b1 I
b1000 $
b1000 6
b1000 M
b101 "
b101 5
b101 L
b110 !
b110 4
b110 K
b100000 +
b100000 :
b100000 >
b100000 O
b1000000011000101000010000110011 0
b1000000011000101000010000110011 3
b1000000011000101000010000110011 J
b1000000011000101000010000110011 Q
b1 2
0W
0V
0U
0[
0Z
1\
b0 X
b0 T
b1 Y
b100000101000100010001000010000001111000001101010010110000100000011110000011011000101100001000000111100000110111 ]
#20000
b1010 )
b1010 9
b1010 S
1.
1#
b0 /
b0 <
b0 H
b10 (
b10 8
b10 I
b10011 %
b10011 7
b10011 =
b10011 N
b10011 R
b101 $
b101 6
b101 M
b110 "
b110 5
b110 L
b1010 !
b1010 4
b1010 K
b0 +
b0 :
b0 >
b0 O
b101000110000001010010011 0
b101000110000001010010011 3
b101000110000001010010011 J
b101000110000001010010011 Q
b10 2
b1 T
b101001101010101010000100010000001111000001110000010110000100000011110000011010100101100001000000111100000110110 ]
#30000
1.
1#
b10 (
b10 8
b10 I
b11100 !
b11100 4
b11100 K
b1111111 +
b1111111 :
b1111111 >
b1111111 O
b11111111111111111111111111111100 )
b11111111111111111111111111111100 9
b11111111111111111111111111111100 S
b11111111110000110000001010010011 0
b11111111110000110000001010010011 3
b11111111110000110000001010010011 J
b11111111110000110000001010010011 Q
b11 2
1U
b1010 X
b0 T
b10 Y
b10000010100010001000100010010010010000001111000001101010010110000100000011110000011011000101100001000000011000100110000 ]
#40000
1'
1.
1#
b11 (
b11 8
b11 I
b11 %
b11 7
b11 =
b11 N
b11 R
b10 ,
b10 ;
b10 ?
b10 P
b100 !
b100 4
b100 K
b0 +
b0 :
b0 >
b0 O
b100 )
b100 9
b100 S
b10000110010001010000011 0
b10000110010001010000011 3
b10000110010001010000011 J
b10000110010001010000011 Q
b100 2
b11111111111111111111111111111100 X
b10000010100010001000100010010010010000001111000001101010010110000100000011110000011011000101100001000000010110100110100 ]
#50000
1&
1.
0'
0#
b100 (
b100 8
b100 I
b100011 %
b100011 7
b100011 =
b100011 N
b100011 R
b100 $
b100 6
b100 M
b101 !
b101 4
b101 K
b100 )
b100 9
b100 S
b10100110010001000100011 0
b10100110010001000100011 3
b10100110010001000100011 J
b10100110010001000100011 Q
b101 2
1Z
b100 X
b11 Y
b10011000101011100100000011110000011010100101100001000000011010000101000011110000011011000101001 ]
#60000
b1 /
b1 <
b1 H
1-
0.
0&
b101 (
b101 8
b101 I
b1100011 %
b1100011 7
b1100011 =
b1100011 N
b1100011 R
b1000 $
b1000 6
b1000 M
b0 ,
b0 ;
b0 ?
b0 P
b101 "
b101 5
b101 L
b110 !
b110 4
b110 K
b1000 )
b1000 9
b1000 S
b11000101000010001100011 0
b11000101000010001100011 3
b11000101000010001100011 J
b11000101000010001100011 Q
b110 2
1[
0Z
0\
b100 Y
b10100110101011100100000011110000011010100101100001000000011010000101000011110000011011000101001 ]
#70000
1*
0-
b0 /
b0 <
b0 H
b0 (
b0 8
b0 I
b1111111 %
b1111111 7
b1111111 =
b1111111 N
b1111111 R
b11111 $
b11111 6
b11111 M
b111 ,
b111 ;
b111 ?
b111 P
b11111 "
b11111 5
b11111 L
b11111 !
b11111 4
b11111 K
b1111111 +
b1111111 :
b1111111 >
b1111111 O
b0 )
b0 9
b0 S
b11111111111111111111111111111111 0
b11111111111111111111111111111111 3
b11111111111111111111111111111111 J
b11111111111111111111111111111111 Q
b111 2
1V
0U
0[
b1000 X
b1 T
b101 Y
b1000010010001010101000100100000011110000011010100101100001000000111100000110110001011000010000000111000 ]
#80000
b1000 2
1W
0V
b0 X
b0 T
b0 Y
b1001001010011000100110001000101010001110100000101001100001000000100100101001110010100110101010001010010010101010100001101010100010010010100111101001110 ]
